{
    "StudyFieldsResponse": {
        "APIVrs": "1.01.05",
        "DataVrs": "2022:06:23 23:12:38.411",
        "Expression": "Duchenne Muscular Dystrophy",
        "NStudiesAvail": 419313,
        "NStudiesFound": 795,
        "MinRank": 1,
        "MaxRank": 10,
        "NStudiesReturned": 10,
        "FieldList": [
            "NCTId",
            "Phase",
            "OverallStatus",
            "DesignPrimaryPurpose"
        ],
        "StudyFields": [
            {
                "Rank": 1,
                "NCTId": [
                    "NCT04740554"
                ],
                "Phase": [],
                "OverallStatus": [
                    "Completed"
                ],
                "DesignPrimaryPurpose": []
            },
            {
                "Rank": 2,
                "NCTId": [
                    "NCT05244395"
                ],
                "Phase": [
                    "Not Applicable"
                ],
                "OverallStatus": [
                    "Completed"
                ],
                "DesignPrimaryPurpose": [
                    "Other"
                ]
            },
            {
                "Rank": 3,
                "NCTId": [
                    "NCT04607824"
                ],
                "Phase": [],
                "OverallStatus": [
                    "Completed"
                ],
                "DesignPrimaryPurpose": []
            },
            {
                "Rank": 4,
                "NCTId": [
                    "NCT05305976"
                ],
                "Phase": [
                    "Not Applicable"
                ],
                "OverallStatus": [
                    "Completed"
                ],
                "DesignPrimaryPurpose": [
                    "Prevention"
                ]
            },
            {
                "Rank": 5,
                "NCTId": [
                    "NCT05249361"
                ],
                "Phase": [],
                "OverallStatus": [
                    "Not yet recruiting"
                ],
                "DesignPrimaryPurpose": []
            },
            {
                "Rank": 6,
                "NCTId": [
                    "NCT03513367"
                ],
                "Phase": [],
                "OverallStatus": [
                    "Unknown status"
                ],
                "DesignPrimaryPurpose": []
            },
            {
                "Rank": 7,
                "NCTId": [
                    "NCT05209087"
                ],
                "Phase": [],
                "OverallStatus": [
                    "Recruiting"
                ],
                "DesignPrimaryPurpose": []
            },
            {
                "Rank": 8,
                "NCTId": [
                    "NCT02069756"
                ],
                "Phase": [],
                "OverallStatus": [
                    "Recruiting"
                ],
                "DesignPrimaryPurpose": []
            },
            {
                "Rank": 9,
                "NCTId": [
                    "NCT02530905"
                ],
                "Phase": [
                    "Phase 1"
                ],
                "OverallStatus": [
                    "Completed"
                ],
                "DesignPrimaryPurpose": [
                    "Treatment"
                ]
            },
            {
                "Rank": 10,
                "NCTId": [
                    "NCT03039686"
                ],
                "Phase": [
                    "Phase 2",
                    "Phase 3"
                ],
                "OverallStatus": [
                    "Completed"
                ],
                "DesignPrimaryPurpose": [
                    "Treatment"
                ]
            }
        ]
    }
}